LICENSE
MANIFEST.in
README.rst
requirements.txt
setup.py
dfva_python/__init__.py
dfva_python/client.py
dfva_python/crypto.py
dfva_python/jmeter_logger.py
dfva_python/manual_test.py
dfva_python/send_files.py
dfva_python/settings.py
dfva_python/test.py
dfva_python.egg-info/PKG-INFO
dfva_python.egg-info/SOURCES.txt
dfva_python.egg-info/dependency_links.txt
dfva_python.egg-info/not-zip-safe
dfva_python.egg-info/requires.txt
dfva_python.egg-info/top_level.txt
dfva_python/tests/__init__.py
dfva_python/tests/authentication.py
dfva_python/tests/builder.py
dfva_python/tests/signer.py
dfva_python/tests/stamp.py
dfva_python/tests/utils.py
dfva_python/tests/validation.py