Metadata-Version: 2.4
Name: dfva-python
Version: 0.0.7
Summary: DFVA client for python.
Home-page: https://github.com/luisza/dfva_python
Author: Luis Zarate
Author-email: luis.zarate@solvosoft.com
License: GNU General Public License v3 (GPLv3)
Platform: OS Independent
Classifier: Environment :: Web Environment
Classifier: Intended Audience :: Developers
Classifier: License :: OSI Approved :: GNU General Public License v3 (GPLv3)
Classifier: Operating System :: OS Independent
Classifier: Programming Language :: Python
Classifier: Programming Language :: Python :: 3.5
Classifier: Programming Language :: Python :: 3.6
Classifier: Topic :: Internet :: WWW/HTTP
Classifier: Topic :: Internet :: WWW/HTTP :: Dynamic Content
Classifier: Topic :: Software Development :: Libraries :: Python Modules
Classifier: Development Status :: 4 - Beta
Classifier: Topic :: Security :: Cryptography
License-File: LICENSE
Requires-Dist: pytz>=2024.1
Requires-Dist: requests>=2.31.0
Requires-Dist: pycryptodome>=3.20.0
Requires-Dist: asn1crypto>=1.5.1
Dynamic: author
Dynamic: author-email
Dynamic: classifier
Dynamic: description
Dynamic: description-content-type
Dynamic: home-page
Dynamic: license
Dynamic: license-file
Dynamic: platform
Dynamic: requires-dist
Dynamic: summary
